tardis/__init__.py
tardis/adapters/__init__.py
tardis/adapters/batchsystems/__init__.py
tardis/adapters/batchsystems/fakebatchsystem.py
tardis/adapters/batchsystems/htcondor.py
tardis/adapters/sites/__init__.py
tardis/adapters/sites/cloudstack.py
tardis/adapters/sites/fakesite.py
tardis/adapters/sites/htcondor.py
tardis/adapters/sites/moab.py
tardis/adapters/sites/openstack.py
tardis/adapters/sites/slurm.py
tardis/agents/__init__.py
tardis/agents/batchsystemagent.py
tardis/agents/siteagent.py
tardis/configuration/__init__.py
tardis/configuration/configuration.py
tardis/configuration/utilities.py
tardis/exceptions/__init__.py
tardis/exceptions/executorexceptions.py
tardis/exceptions/tardisexceptions.py
tardis/interfaces/__init__.py
tardis/interfaces/batchsystemadapter.py
tardis/interfaces/borg.py
tardis/interfaces/executor.py
tardis/interfaces/plugin.py
tardis/interfaces/simulator.py
tardis/interfaces/siteadapter.py
tardis/interfaces/state.py
tardis/plugins/__init__.py
tardis/plugins/sqliteregistry.py
tardis/plugins/telegrafmonitoring.py
tardis/resources/__init__.py
tardis/resources/drone.py
tardis/resources/dronestates.py
tardis/resources/poolfactory.py
tardis/utilities/__init__.py
tardis/utilities/asynccachemap.py
tardis/utilities/attributedict.py
tardis/utilities/pipeline.py
tardis/utilities/staticmapping.py
tardis/utilities/utils.py
tardis/utilities/executors/__init__.py
tardis/utilities/executors/shellexecutor.py
tardis/utilities/executors/sshexecutor.py
tardis/utilities/simulators/__init__.py
tardis/utilities/simulators/periodicvalue.py
tardis/utilities/simulators/randomgauss.py
tests/adapters_t/__init__.py
tests/adapters_t/batchsystems_t/__init__.py
tests/adapters_t/batchsystems_t/test_fakebatchsystem.py
tests/adapters_t/batchsystems_t/test_htcondor.py
tests/adapters_t/sites_t/__init__.py
tests/adapters_t/sites_t/test_cloudstack.py
tests/adapters_t/sites_t/test_fakesite.py
tests/adapters_t/sites_t/test_htcondorsiteadapter.py
cobald_tardis-0.2.0.dist-info/LICENSE.txt
cobald_tardis-0.2.0.dist-info/METADATA
cobald_tardis-0.2.0.dist-info/WHEEL
cobald_tardis-0.2.0.dist-info/top_level.txt
cobald_tardis-0.2.0.dist-info/RECORD
