Metadata-Version: 2.1
Name: cobald-tardis
Version: 0.2.0
Summary: Transparent Adaptive Resource Dynamic Integration System
Home-page: https://github.com/matterminers/tardis
Author: Manuel Giffels
Author-email: giffels@gmail.com
License: UNKNOWN
Project-URL: Bug Reports, https://github.com/matterminers/tardis/issues
Project-URL: Source, https://github.com/materminers/tardis
Keywords: asyncio tardis cloud scheduler
Platform: UNKNOWN
Classifier: Development Status :: 3 - Alpha
Classifier: Intended Audience :: Developers
Classifier: Intended Audience :: System Administrators
Classifier: Intended Audience :: Information Technology
Classifier: Intended Audience :: Science/Research
Classifier: Operating System :: OS Independent
Classifier: Topic :: System :: Distributed Computing
Classifier: Topic :: Scientific/Engineering :: Physics
Classifier: Topic :: Utilities
Classifier: Framework :: AsyncIO
Classifier: License :: OSI Approved :: MIT License
Classifier: Programming Language :: Python :: 3.6
Classifier: Programming Language :: Python :: 3.7
Requires-Dist: aiohttp
Requires-Dist: CloudStackAIO
Requires-Dist: PyYAML
Requires-Dist: AsyncOpenStackClient
Requires-Dist: cobald
Requires-Dist: asyncssh
Requires-Dist: aiotelegraf
